README.rst
setup.py
bitscrooge_client.egg-info/PKG-INFO
bitscrooge_client.egg-info/SOURCES.txt
bitscrooge_client.egg-info/dependency_links.txt
bitscrooge_client.egg-info/not-zip-safe
bitscrooge_client.egg-info/top_level.txt
foo/__init__.py